AUTHORS
CHANGES.rst
LICENSE
MANIFEST.in
README.rst
setup.cfg
setup.py
pysym/__init__.py
pysym/_release.py
pysym/core.py
pysym/util.py
pysym.egg-info/PKG-INFO
pysym.egg-info/SOURCES.txt
pysym.egg-info/dependency_links.txt
pysym.egg-info/top_level.txt
pysym/tests/__init__.py
pysym/tests/test_core.py
pysym/tests/test_deprecation.py
pysym/tests/test_lambdify.py
pysym/tests/test_matrix.py
pysym/tests/test_util.py