Metadata-Version: 1.1
Name: pysym
Version: 0.2.0
Summary: Minimal symbolic manipulation framework.
Home-page: https://github.com/bjodah/pysym
Author: Björn Dahlgren
Author-email: bjodah@DELETEMEgmail.com
License: BSD
Platform: UNKNOWN
Classifier: Development Status :: 3 - Alpha
Classifier: License :: OSI Approved :: BSD License
Classifier: Operating System :: OS Independent
Classifier: Topic :: Scientific/Engineering
Classifier: Topic :: Scientific/Engineering :: Mathematics
